bit_xly/__init__.py
bit_xly/client.py
bit_xly/models.py
bit_xly/provider.py
bit_xly/xmly_api.py
bit_xly-1.0.0.dist-info/licenses/LICENSE
bit_xly-1.0.0.dist-info/METADATA
bit_xly-1.0.0.dist-info/WHEEL
bit_xly-1.0.0.dist-info/top_level.txt
bit_xly-1.0.0.dist-info/RECORD
